fds/__init__.py
fds/sdk/__init__.py
fds/sdk/SecurityIntelligence/__init__.py
fds/sdk/SecurityIntelligence/api_client.py
fds/sdk/SecurityIntelligence/configuration.py
fds/sdk/SecurityIntelligence/exceptions.py
fds/sdk/SecurityIntelligence/model_utils.py
fds/sdk/SecurityIntelligence/rest.py
fds/sdk/SecurityIntelligence/api/__init__.py
fds/sdk/SecurityIntelligence/api/company_summary_api.py
fds/sdk/SecurityIntelligence/api/stock_movement_summary_api.py
fds/sdk/SecurityIntelligence/apis/__init__.py
fds/sdk/SecurityIntelligence/model/__init__.py
fds/sdk/SecurityIntelligence/model/competitor.py
fds/sdk/SecurityIntelligence/model/custom_validation_error.py
fds/sdk/SecurityIntelligence/model/debt_summary_response.py
fds/sdk/SecurityIntelligence/model/error_item.py
fds/sdk/SecurityIntelligence/model/events_summary_response.py
fds/sdk/SecurityIntelligence/model/financial_highlights_response.py
fds/sdk/SecurityIntelligence/model/meta_data.py
fds/sdk/SecurityIntelligence/model/mna_summary_response.py
fds/sdk/SecurityIntelligence/model/ownership_insights_response.py
fds/sdk/SecurityIntelligence/model/reference.py
fds/sdk/SecurityIntelligence/model/server_error.py
fds/sdk/SecurityIntelligence/model/stock_movement_item.py
fds/sdk/SecurityIntelligence/model/stock_movement_meta_data.py
fds/sdk/SecurityIntelligence/model/stock_movement_response.py
fds/sdk/SecurityIntelligence/model/summary_item.py
fds/sdk/SecurityIntelligence/models/__init__.py
fds_sdk_securityintelligence-0.1.0.dist-info/licenses/LICENSE
fds_sdk_securityintelligence-0.1.0.dist-info/METADATA
fds_sdk_securityintelligence-0.1.0.dist-info/WHEEL
fds_sdk_securityintelligence-0.1.0.dist-info/top_level.txt
fds_sdk_securityintelligence-0.1.0.dist-info/RECORD
